vulnscan/__init__.py
vulnscan/cli.py
vulnscan/main.py
vulnscan/pdf_vulnscan_updated.py
vulnscan/base/__init__.py
vulnscan/base/colors.py
vulnscan/base/crawl.py
vulnscan/base/entropy.py
vulnscan/base/extractHTMLInformation.py
vulnscan/base/formEvaluate.py
vulnscan/base/formParser.py
vulnscan/base/modifyManipulateAPI.py
vulnscan/base/prompt.py
vulnscan/base/rangeFinder.py
vulnscan/base/sendRequest.py
vulnscan/base/testing.py
vulnscan/base/utils.py
vulnscan/db/__init__.py
vulnscan/modules/__init__.py
vulnscan/modules/advanced_api_checking.py
vulnscan/modules/advanced_reporting.py
vulnscan/modules/ai_powered_checking.py
vulnscan/modules/cloud_vulnerability_checking.py
vulnscan/modules/domain_passive_active_check.py
vulnscan/modules/modern_security_platform.py
vulnscan/modules/security_tool_integration.py
vulnscan/modules/web_app_checking.py
vulnscan/venv/__init__.py
vulnscan/venv/bin/jp.py
vulnscan-3.2.0.dist-info/licenses/LICENSE
vulnscan-3.2.0.dist-info/METADATA
vulnscan-3.2.0.dist-info/WHEEL
vulnscan-3.2.0.dist-info/entry_points.txt
vulnscan-3.2.0.dist-info/top_level.txt
vulnscan-3.2.0.dist-info/RECORD
